CHANGELOG.md
LICENSE
MANIFEST.in
README.md
setup.py
tox.ini
doc/layout_file.md
ear/__init__.py
ear/common.py
ear/compatibility.py
ear/conftest.py
ear/options.py
ear.egg-info/PKG-INFO
ear.egg-info/SOURCES.txt
ear.egg-info/dependency_links.txt
ear.egg-info/entry_points.txt
ear.egg-info/requires.txt
ear.egg-info/top_level.txt
ear/cmdline/__init__.py
ear/cmdline/ambix_to_bwf.py
ear/cmdline/dev_config.py
ear/cmdline/error_handler.py
ear/cmdline/generate_test_file.py
ear/cmdline/render_file.py
ear/cmdline/utils.py
ear/cmdline/test/__init__.py
ear/cmdline/test/test_utils.py
ear/core/__init__.py
ear/core/allocentric.py
ear/core/block_aligner.py
ear/core/bs2051.py
ear/core/convolver.py
ear/core/delay.py
ear/core/geom.py
ear/core/hoa.py
ear/core/importance.py
ear/core/layout.py
ear/core/metadata_input.py
ear/core/metadata_processing.py
ear/core/monitor.py
ear/core/plot_point_source.py
ear/core/point_source.py
ear/core/renderer.py
ear/core/renderer_common.py
ear/core/screen_common.py
ear/core/screen_edge_lock.py
ear/core/screen_scale.py
ear/core/track_processor.py
ear/core/util.py
ear/core/data/2051_layouts.yaml
ear/core/data/Design_5200_100_random.dat
ear/core/data/README.md
ear/core/data/allo_positions.yaml
ear/core/direct_speakers/__init__.py
ear/core/direct_speakers/panner.py
ear/core/direct_speakers/renderer.py
ear/core/direct_speakers/test/__init__.py
ear/core/direct_speakers/test/test_panner.py
ear/core/objectbased/__init__.py
ear/core/objectbased/allo_extent.py
ear/core/objectbased/conversion.py
ear/core/objectbased/decorrelate.py
ear/core/objectbased/extent.py
ear/core/objectbased/gain_calc.py
ear/core/objectbased/renderer.py
ear/core/objectbased/zone.py
ear/core/objectbased/test/__init__.py
ear/core/objectbased/test/conftest.py
ear/core/objectbased/test/test_allo_extent.py
ear/core/objectbased/test/test_channel_lock.py
ear/core/objectbased/test/test_conversion.py
ear/core/objectbased/test/test_decorrelate.py
ear/core/objectbased/test/test_extent.py
ear/core/objectbased/test/test_gain_calc.py
ear/core/objectbased/test/test_gain_calc_changes.py
ear/core/objectbased/test/test_renderer.py
ear/core/objectbased/test/test_zone.py
