Metadata-Version: 2.1
Name: ear
Version: 2.1.0
Summary: EBU ADM Renderer
Home-page: https://github.com/ebu/ebu_adm_renderer
Author: EBU
Author-email: ear-admin@list.ebu.ch
License: BSD-3-Clause-Clear
Platform: UNKNOWN
Provides-Extra: test
Provides-Extra: dev
License-File: LICENSE
